funpayace/__init__.py
funpayace-0.1.0.dist-info/licenses/LICENSE
funpayace-0.1.0.dist-info/METADATA
funpayace-0.1.0.dist-info/WHEEL
funpayace-0.1.0.dist-info/top_level.txt
funpayace-0.1.0.dist-info/RECORD
