Metadata-Version: 2.4
Name: FunpayACE
Version: 0.1.0
Summary: Библиотека для удобного управления Funpay
Author: Looko
License: MIT
Requires-Python: >=3.7
License-File: LICENSE
Requires-Dist: aiohttp<4.0,>=3.7
Requires-Dist: beautifulsoup4>=4.9.3
Dynamic: license-file
